{"data":{"allMarkdownRemark":{"edges":[{"node":{"excerpt":"In this book, the first of its kind written by a scientific expert, Professor Matthew Walker…","id":"bcde4d28-22ea-5373-b0ba-12fedafb8611","fields":{"slug":"/resources/why-we-sleep/"},"frontmatter":{"resourceDescription":"The new science of sleep and dreams","image":"/img/why-we-sleep.jpg","resourceName":"Why We Sleep","resourceImage":"/img/why-we-sleep-2-.jpg","resourcePrice":"$18","resourceLink":"https://www.bookdepository.com/Why-We-Sleep-Matthew-Walker/9780141983769?redirected=true&utm_medium=Google&utm_campaign=Base1&utm_source=NZ&utm_content=Why-We-Sleep&selectCurrency=NZD&w=AF7CAU99ZZCHQQA809DF&pdg=pla-309174813119:kwd-309174813119:cmp-947803846:adg-45233890537:crv-225027758847:pid-9780141983769:dev-c&gclid=CjwKCAiA9efgBRAYEiwAUT-jtC9VPEhWV98-4hvePej-jaUIMt9i0tue_FW53REhyB5q7SWy3e5wlhoC5WUQAvD_BwE","date":"December 19, 2018"}}},{"node":{"excerpt":"At the cutting edge of the latest science, What the Fast! is a practical guide to get you started…","id":"b94e7319-2a6d-54ee-b882-b30c23b61a2c","fields":{"slug":"/resources/what-the-fast/"},"frontmatter":{"resourceDescription":"Fasting","image":"/img/detail.hfjn-5548-ga50.0.photo.192825750x.jpg","resourceName":"What the Fast","resourceImage":"/img/detail.hfjn-5548-ga50.0.photo.192825750x-2-.jpg","resourcePrice":"$34.95","resourceLink":"https://whatthefatbook.com/product/what-the-fast/","date":"December 18, 2018"}}},{"node":{"excerpt":"A clinical exercise physiologist can be defined as an individual who specialises in the delivery of…","id":"ebeccc48-8dd0-5ff8-81ca-90fdae7fc2ee","fields":{"slug":"/resources/clinical-exercise-physiologist/"},"frontmatter":{"resourceDescription":"Find a Clinical Exercise Phsiologist","image":"/img/xexercise-physiology-banner.jpg.pagespeed.ic.mj-ciyjfc-.jpg","resourceName":"Clinical Exercise Physiologist","resourceImage":"/img/xexercise-physiology-banner.jpg.pagespeed.ic.mj-ciyjfc-.jpg","resourcePrice":"Varies","resourceLink":"https://www.cepnz.org.nz/","date":"December 18, 2018"}}},{"node":{"excerpt":"This great book shows you how to Relax, Eat, Move and Sleep your way to a longer, healthier life…","id":"b2ed334a-6661-578f-bd59-fb11361c57b5","fields":{"slug":"/resources/the-4-pillar-plan/"},"frontmatter":{"resourceDescription":"This great book shows you how to Relax, Eat, Move and Sleep your way to a longer, healthier life.easy to read ","image":"/img/4-pillar-plan.jpg","resourceName":"The 4 Pillar Plan","resourceImage":"/img/4-pillar-plan.jpg","resourcePrice":"About $30. ","resourceLink":"https://www.fishpond.co.nz/Books/4-Pillar-Plan-Dr-Rangan-Chatterjee/9780241303559?utm_source=googleps&utm_medium=ps&utm_campaign=NZ&gclid=Cj0KCQiAr93gBRDSARIsADvHiOpiyDfcbDeDkGJk220M9qtPqlY8rLnWlSdfsBLbdmYZdb_ohP6fmBkaAs36EALw_wcB#.XBiXzxx-OMo.email","date":"December 18, 2018"}}},{"node":{"excerpt":"Download the free Prekure food guidelines as recommended by internationally respected Dietitian…","id":"aca5c87f-38d6-577f-8ad9-e5193724c959","fields":{"slug":"/resources/the-prekure-food-guidelines/"},"frontmatter":{"resourceDescription":"Food guidelines","image":"/img/43273662_10157139518294369_3797070441957294080_n.jpg","resourceName":"Prekure Food Guidelines","resourceImage":"/img/small-food.jpg","resourcePrice":"Free","resourceLink":"https://www.prekure.com/food-guidelines/","date":"December 18, 2018"}}}]}},"pageContext":{"id":"f1221472-d703-555e-a8c7-2e853fd36dda"}}