{"data":{"markdownRemark":{"id":"21a0b4f8-59ef-501d-aaec-c7293eca5187","html":"<p>Lisa is a Medical Oncologist working in Northland New Zealand. She practices in both the public hospital and for Canopy Cancer Care in private practice. She started the Cancer and blood services in Northland in 2014 and was clinical director for 3 years.   Under her leadership the Cancer and blood services won the DHB award for 'Outstanding Model of Care'. Lisa has a particular interest in breast cancer.<br>\n<br>\nLisa is a member of the Society of Integrative Oncology whose mission it is to advance evidence-based, comprehensive, integrative healthcare to improve the lives of people affected by cancer.  </p>\n<p><br>\nIn 2018 Lisa joined the faculty of Prekure - a social enterprise that exists to inspire a change in medicine to be more focused on prevention through lifestyle as medicine.<br>\n<br>\nWhen not working, she is running around with the kids,  walking her beloved dog Molly or sailing on the family boat. She also loves riding horses, eating food and reading books. The family are active in their local church.</p>","frontmatter":{"title":"Dr Lisa Dawson","full_image":"/img/lisa-2-.jpg","leftBackground":"/img/lisa-2-.jpg","leftTitle":"View All Our Resources","leftLink":"https://www.whatthecancer.com/resources","rightTitle":"What The Cancer?","rightDescription":"Resources","rightUrl":"https://www.prekure.com/"}}},"pageContext":{"id":"21a0b4f8-59ef-501d-aaec-c7293eca5187"}}