{"data":{"markdownRemark":{"id":"576c1608-0625-5c33-b071-c0b97ccc8337","html":"<h2>A</h2>\n<p>  Amazing stuff <br>\nAmazing stuff <br>\nAmazing stuff </p>\n<h2>B</h2>\n<p>  Amazing stuff <br>\nAmazing stuff <br>\nAmazing stuff </p>\n<h2>C</h2>\n<p>  Amazing stuff <br>\nAmazing stuff <br>\nAmazing stuff </p>\n<h2>D</h2>\n<p>  Amazing stuff <br>\nAmazing stuff <br>\nAmazing stuff </p>\n<h2>E</h2>\n<p>  Amazing stuff <br>\nAmazing stuff <br>\nAmazing stuff </p>\n<h2>F</h2>\n<p>  Amazing stuff <br>\nAmazing stuff <br>\nAmazing stuff </p>\n<h2>G</h2>\n<p>  Amazing stuff <br>\nAmazing stuff <br>\nAmazing stuff </p>\n<h2>H</h2>\n<p>  Amazing stuff <br>\nAmazing stuff <br>\nAmazing stuff </p>\n<h2>I</h2>\n<p>  Amazing stuff <br>\nAmazing stuff <br>\nAmazing stuff</p>","frontmatter":{"title":"Jargon Dictionary","full_image":"/img/resource-splash.jpg","leftBackground":"/img/resource-splash.jpg","leftTitle":"View All Our Resources","leftLink":"https://www.whatthecancer.com/resources","rightTitle":"Read our Blog","rightDescription":"Read, Listen or Watch articles on topics relating to fighting and prevention of cancer","rightUrl":"/blog"}}},"pageContext":{"id":"576c1608-0625-5c33-b071-c0b97ccc8337"}}